cloudauthz/__init__.py
cloudauthz/exceptions.py
cloudauthz/interfaces/__init__.py
cloudauthz/interfaces/providers.py
cloudauthz/providers/__init__.py
cloudauthz/providers/aws.py
cloudauthz/providers/azure.py
cloudauthz/providers/gcp.py
cloudauthz_tests/__init__.py
cloudauthz-0.6.0.dist-info/LICENSE
cloudauthz-0.6.0.dist-info/METADATA
cloudauthz-0.6.0.dist-info/WHEEL
cloudauthz-0.6.0.dist-info/top_level.txt
cloudauthz-0.6.0.dist-info/RECORD
