Metadata-Version: 2.1
Name: cloudauthz
Version: 0.6.0
Summary: Implements means of authorization delegation on cloud-based resource providers.
Home-page: https://github.com/galaxyproject/cloudauthz
Author: The Galaxy Team
Author-email: jalili.vahid@gmail.com
License: MIT
Keywords: Cloud Authorization
Platform: UNKNOWN
Classifier: Development Status :: 3 - Alpha
Classifier: Intended Audience :: Developers
